utils/__init__.py
utlz/__init__.py
utlz-0.3.0.dist-info/DESCRIPTION.rst
utlz-0.3.0.dist-info/METADATA
utlz-0.3.0.dist-info/RECORD
utlz-0.3.0.dist-info/WHEEL
utlz-0.3.0.dist-info/metadata.json
utlz-0.3.0.dist-info/top_level.txt
